{
	"code": "clayformer",
	"class": "BlockClayformer",
	"entityclass": "BEEAssembler",
	"entityBehaviors": [ { "name": "Animatable" } ],
	"creativeinventory": {
		"general": [ "*-east" ],
		"qptech": [ "*-east" ]
	},
	"variantgroups": [
		{ code: "type", states: ["bowl", "clayplanter","flowerpot","ingotmold","testingot"] },
		{
			"code": "side",
			"loadFromProperties": "abstract/horizontalorientation"
		}
	],
	"behaviors": [
		{
			"name": "HorizontalOrientable",
			"properties": { "dropBlockFace": "east" }
		}
	],
	
	"attributesbytype":{
		
		"*-bowl-*":{
			"maxAmps": 2,
			"maxVolts": 16,
			"capacitance": 2,
			"requiredAmps": 2,
			"inputFace": "west",
			"outputFace": "east",
			"inputQuantity": 4,
			"outputQuantity": 1,
			"recipe": "game:bowl-raw",
			"ingredient": "game:clay-blue",
			"processingTime": 0.17,
			"animationSpeed": 0.05,
			
		},
		"*-clayplanter-*":{
			"maxAmps": 2,
			"maxVolts": 16,
			"capacitance": 2,
			"requiredAmps": 2,
			"inputFace": "west",
			"outputFace": "east",
			"inputQuantity": 12,
			"outputQuantity": 1,
			"recipe": "game:clayplanter-raw",
			"ingredient": "game:clay-blue",
			"processingTime": 0.25,
			"animationSpeed": 0.04
		},
		"*-flowerpot-*":{
			"maxAmps": 2,
			"maxVolts": 16,
			"capacitance": 2,
			"requiredAmps": 2,
			"inputFace": "west",
			"outputFace": "east",
			"inputQuantity": 10,
			"outputQuantity": 1,
			"recipe": "game:flowerpot-raw",
			"ingredient": "game:clay-blue",
			"processingTime": 0.25,
			"animationSpeed": 0.04
		},
		"*-ingotmold-*":{
			"maxAmps": 2,
			"maxVolts": 16,
			"capacitance": 2,
			"requiredAmps": 2,
			"inputFace": "west",
			"outputFace": "east",
			"inputQuantity": 4,
			"outputQuantity": 1,
			"recipe": "game:ingotmold-raw",
			"ingredient": "game:clay-blue",
			"processingTime": 0.17,
			"animationSpeed": 0.05
		},
		"*-testingot-*":{
			"maxAmps": 2,
			"maxVolts": 16,
			"capacitance": 2,
			"requiredAmps": 2,
			"inputFace": "west",
			"outputFace": "east",
			"inputQuantity": 2,
			"outputQuantity": 1,
			"recipe": "game:metalplate-copper",
			"ingredient": "game:ingot-copper",
			"processingTime": 0.01,
			"animationSpeed": 0.05,
			"heatRequirement": 1000,
			"blockoritem": "item"
		},
	},
	"blockmaterial": "Metal",
	"drawtype": "json",

	"shape": { "base": "block/clayformer-bowl" },
	"shapeByType": {
		"*-north": {
			"base": "block/clayformer-bowl",
			"rotateY": 0
		},
		"*-east": {
			"base": "block/clayformer-bowl",
			"rotateY": 270
		},
		"*-west": {
			"base": "block/clayformer-bowl",
			"rotateY": 90
		},
		"*-south": {
			"base": "block/clayformer-bowl",
			"rotateY": 180
		}
	},
	"resistance": 1,
	"sideAo": { "all": false },
	"sidesolid": {
		"all": false
	},
	"sideopaque": {
		"all": false
	},
	"sounds": {
		"place": "game:block/anvil",
		"walk": "game:walk/stone"
	}


}